blackdz6Koldunov/__init__.py
blackdz6Koldunov/__main__.py
blackdz6Koldunov/order_management.py
blackdz6Koldunov/user_management.py
blackdz6Koldunov-0.1.0.dist-info/METADATA
blackdz6Koldunov-0.1.0.dist-info/WHEEL
blackdz6Koldunov-0.1.0.dist-info/entry_points.txt
blackdz6Koldunov-0.1.0.dist-info/top_level.txt
blackdz6Koldunov-0.1.0.dist-info/RECORD
