Metadata-Version: 2.1
Name: blackdz6Koldunov
Version: 0.1.0
Summary: Исполняемый пакет для управления пользователями и заказами в онлайн-магазине
Author-email: Grisha <g.koldunov@edu.centraluniversity.ru>
License: MIT
Requires-Python: >=3.8
